geotiler/__init__.py
geotiler/cache.py
geotiler/data.py
geotiler/errors.py
geotiler/geo.py
geotiler/map.py
geotiler/provider.py
geotiler/py.typed
geotiler/util.py
geotiler/source/bluemarble.json
geotiler/source/osm.json
geotiler/source/stamen-terrain-background.json
geotiler/source/stamen-terrain-lines.json
geotiler/source/stamen-terrain.json
geotiler/source/stamen-toner-lite.json
geotiler/source/stamen-toner.json
geotiler/source/stamen-watercolor.json
geotiler/source/thunderforest-cycle.json
geotiler/tests/__init__.py
geotiler/tests/test_cache.py
geotiler/tests/test_geo.py
geotiler/tests/test_map.py
geotiler/tests/test_provider.py
geotiler/tests/test_tile_img.py
geotiler/tests/test_tile_io.py
geotiler/tests/test_util.py
geotiler/tile/__init__.py
geotiler/tile/img.py
geotiler/tile/io.py
geotiler-0.14.5.data/scripts/geotiler-fetch
geotiler-0.14.5.data/scripts/geotiler-lint
geotiler-0.14.5.data/scripts/geotiler-route
geotiler-0.14.5.dist-info/COPYING
geotiler-0.14.5.dist-info/METADATA
geotiler-0.14.5.dist-info/WHEEL
geotiler-0.14.5.dist-info/top_level.txt
geotiler-0.14.5.dist-info/RECORD
