Metadata-Version: 2.1
Name: geotiler
Version: 0.14.5
Summary: GeoTiler - library to create maps using tiles from a map provider
Home-page: https://wrobell.dcmod.org/geotiler/
Author: Artur Wroblewski
Author-email: wrobell@riseup.net
License: GPL (includes BSD licensed code)
Project-URL: Code, https://github.com/wrobell/geotiler
Project-URL: Bug tracker, https://github.com/wrobell/geotiler/issues
Platform: UNKNOWN
Classifier: Topic :: Scientific/Engineering :: GIS
Classifier: License :: OSI Approved :: GNU General Public License v3 or later (GPLv3+)
Classifier: License :: OSI Approved :: BSD License
Classifier: Programming Language :: Python :: 3.7
Classifier: Development Status :: 4 - Beta
Requires-Python: >=3.8
License-File: COPYING
Requires-Dist: Pillow
Requires-Dist: cytoolz (>=0.8.2)
Requires-Dist: aiohttp (>=2.3.5)
Provides-Extra: tests
Requires-Dist: mypy ; extra == 'tests'
Requires-Dist: pytest-cov ; extra == 'tests'
Requires-Dist: pytest-timeout ; extra == 'tests'
Requires-Dist: pytest-asyncio ; extra == 'tests'
Requires-Dist: uvloop ; extra == 'tests'
